<?xml version="1.0" encoding="utf-8"?>
<Signalliste>
	<Signal>
		<Name>Signal_Ausfahrt_L1</Name>
    <Adresse>300</Adresse>
    <Typ>3B_270</Typ>
		<Adr1Zustand1>0</Adr1Zustand1>
		<Adr1Zustand2>2</Adr1Zustand2>
		<Adr2Zustand1>0</Adr2Zustand1>
		<Adr2Zustand2>0</Adr2Zustand2>
	</Signal>
	<Signal>
		<Name>Signal_Ausfahrt_L2</Name>
    <Adresse>301</Adresse>
    <Typ>3B_270</Typ>
		<Adr1Zustand1>0</Adr1Zustand1>
		<Adr1Zustand2>1</Adr1Zustand2>
		<Adr2Zustand1>0</Adr2Zustand1>
		<Adr2Zustand2>0</Adr2Zustand2>
	</Signal>
	<Signal>
		<Name>Signal_Ausfahrt_L3</Name>
    <Adresse>302</Adresse>
    <Typ>3B_270</Typ>
		<Adr1Zustand1>0</Adr1Zustand1>
		<Adr1Zustand2>1</Adr1Zustand2>
		<Adr2Zustand1>0</Adr2Zustand1>
		<Adr2Zustand2>0</Adr2Zustand2>
	</Signal>
	<Signal>
		<Name>Signal_Ausfahrt_L4</Name>
    <Adresse>303</Adresse>
    <Typ>3B_270</Typ>
		<Adr1Zustand1>0</Adr1Zustand1>
		<Adr1Zustand2>2</Adr1Zustand2>
		<Adr2Zustand1>0</Adr2Zustand1>
		<Adr2Zustand2>0</Adr2Zustand2>
	</Signal>
	<Signal>
		<Name>Signal_Ausfahrt_L5</Name>
    <Adresse>304</Adresse>
    <Typ>3B_270</Typ>
		<Adr1Zustand1>0</Adr1Zustand1>
		<Adr1Zustand2>2</Adr1Zustand2>
		<Adr2Zustand1>0</Adr2Zustand1>
		<Adr2Zustand2>0</Adr2Zustand2>
	</Signal>
	<Signal>
		<Name>Signal_Ausfahrt_L6</Name>
    <Adresse>305</Adresse>
    <Typ>3B_270</Typ>
		<Adr1Zustand1>0</Adr1Zustand1>
		<Adr1Zustand2>2</Adr1Zustand2>
		<Adr2Zustand1>0</Adr2Zustand1>
		<Adr2Zustand2>0</Adr2Zustand2>
	</Signal>
  <Signal>
    <Name>Signal_Ausfahrt_R1</Name>
    <Adresse>306</Adresse>
    <Typ>3B_90</Typ>
    <Adr1Zustand1>0</Adr1Zustand1>
    <Adr1Zustand2>2</Adr1Zustand2>
    <Adr2Zustand1>0</Adr2Zustand1>
    <Adr2Zustand2>0</Adr2Zustand2>
  </Signal>
  <Signal>
    <Name>Signal_Ausfahrt_R2</Name>
    <Adresse>307</Adresse>
    <Typ>3B_90</Typ>
    <Adr1Zustand1>0</Adr1Zustand1>
    <Adr1Zustand2>1</Adr1Zustand2>
    <Adr2Zustand1>0</Adr2Zustand1>
    <Adr2Zustand2>0</Adr2Zustand2>
  </Signal>
  <Signal>
    <Name>Signal_Ausfahrt_R3</Name>
    <Adresse>308</Adresse>
    <Typ>3B_90</Typ>
    <Adr1Zustand1>0</Adr1Zustand1>
    <Adr1Zustand2>1</Adr1Zustand2>
    <Adr2Zustand1>0</Adr2Zustand1>
    <Adr2Zustand2>0</Adr2Zustand2>
  </Signal>
  <Signal>
    <Name>Signal_Ausfahrt_R4</Name>
    <Adresse>309</Adresse>
    <Typ>3B_90</Typ>
    <Adr1Zustand1>0</Adr1Zustand1>
    <Adr1Zustand2>2</Adr1Zustand2>
    <Adr2Zustand1>0</Adr2Zustand1>
    <Adr2Zustand2>0</Adr2Zustand2>
  </Signal>
  <Signal>
    <Name>Signal_Ausfahrt_R5</Name>
    <Adresse>310</Adresse>
    <Typ>3B_90</Typ>
    <Adr1Zustand1>0</Adr1Zustand1>
    <Adr1Zustand2>2</Adr1Zustand2>
    <Adr2Zustand1>0</Adr2Zustand1>
    <Adr2Zustand2>0</Adr2Zustand2>
  </Signal>
  <Signal>
    <Name>Signal_Ausfahrt_R6</Name>
    <Adresse>311</Adresse>
    <Typ>3B_90</Typ>
    <Adr1Zustand1>0</Adr1Zustand1>
    <Adr1Zustand2>2</Adr1Zustand2>
    <Adr2Zustand1>0</Adr2Zustand1>
    <Adr2Zustand2>0</Adr2Zustand2>
  </Signal>
  <Signal>
    <Name>Signal_RTunnel_1</Name>
    <Adresse>312</Adresse>
    <Typ>3B_270</Typ>
    <Adr1Zustand1>0</Adr1Zustand1>
    <Adr1Zustand2>2</Adr1Zustand2>
    <Adr2Zustand1>0</Adr2Zustand1>
    <Adr2Zustand2>0</Adr2Zustand2>
  </Signal>
  <Signal>
    <Name>Signal_RTunnel_2</Name>
    <Adresse>313</Adresse>
    <Typ>3B_270</Typ>
    <Adr1Zustand1>0</Adr1Zustand1>
    <Adr1Zustand2>1</Adr1Zustand2>
    <Adr2Zustand1>0</Adr2Zustand1>
    <Adr2Zustand2>0</Adr2Zustand2>
  </Signal>
  <Signal>
    <Name>Signal_Einfahrt_L</Name>
    <Adresse>314</Adresse>
    <Typ>3B_90</Typ>
    <Adr1Zustand1>0</Adr1Zustand1>
    <Adr1Zustand2>1</Adr1Zustand2>
    <Adr2Zustand1>0</Adr2Zustand1>
    <Adr2Zustand2>0</Adr2Zustand2>
  </Signal>
  <Signal>
    <Name>Signal_Tunnel_L1</Name>
    <Adresse>315</Adresse>
    <Typ>2B_270</Typ>
    <Adr1Zustand1>0</Adr1Zustand1>
    <Adr1Zustand2>1</Adr1Zustand2>
    <Adr2Zustand1>0</Adr2Zustand1>
    <Adr2Zustand2>0</Adr2Zustand2>
  </Signal>
   
</Signalliste>